retractometrics/__init__.py
retractometrics-0.0.15.dist-info/LICENSE.txt
retractometrics-0.0.15.dist-info/METADATA
retractometrics-0.0.15.dist-info/WHEEL
retractometrics-0.0.15.dist-info/entry_points.txt
retractometrics-0.0.15.dist-info/top_level.txt
retractometrics-0.0.15.dist-info/RECORD
