Metadata-Version: 2.2
Name: retractometrics
Version: 0.0.15
Summary: A package for bibliometric analysis of retracted papers
Home-page: 
Author: Anoop Reddy Kallem
Keywords: retracted papers,bibliometrics
Classifier: Programming Language :: Python :: 3
Classifier: License :: OSI Approved :: MIT License
Classifier: Operating System :: OS Independent
Requires-Python: >=3.6
License-File: LICENSE.txt
Requires-Dist: pandas
Requires-Dist: numpy
Requires-Dist: bump2version
Requires-Dist: chardet
Dynamic: author
Dynamic: classifier
Dynamic: description
Dynamic: description-content-type
Dynamic: keywords
Dynamic: requires-dist
Dynamic: requires-python
Dynamic: summary
